oxr/__init__.py
oxr/exceptions.py
oxr/oxr.py
oxr_client-0.1.0.dist-info/DESCRIPTION.rst
oxr_client-0.1.0.dist-info/METADATA
oxr_client-0.1.0.dist-info/metadata.json
oxr_client-0.1.0.dist-info/RECORD
oxr_client-0.1.0.dist-info/top_level.txt
oxr_client-0.1.0.dist-info/WHEEL
