Metadata-Version: 2.0
Name: oxr-client
Version: 0.1.0
Summary: A client for open exchange rates
Home-page: https://github.com/jcomo/oxr-client
Author: Jonathan Como
Author-email: jonathan.como@gmail.com
License: UNKNOWN
Keywords: development client open exchange rates
Platform: UNKNOWN
Classifier: Programming Language :: Python :: 2
Classifier: Programming Language :: Python :: 2.6
Classifier: Programming Language :: Python :: 2.7
Requires-Dist: requests
